{
  "generated_at": "2026-04-25T10:44:53.097Z",
  "sites": [
    {
      "site_id": "techurls",
      "site_name": "TechURLs",
      "ok": true,
      "item_count": 405,
      "duration_ms": 524,
      "error": null
    },
    {
      "site_id": "buzzing",
      "site_name": "Buzzing",
      "ok": true,
      "item_count": 744,
      "duration_ms": 218,
      "error": null
    },
    {
      "site_id": "iris",
      "site_name": "Info Flow",
      "ok": true,
      "item_count": 395,
      "duration_ms": 12813,
      "error": null
    },
    {
      "site_id": "bestblogs",
      "site_name": "BestBlogs",
      "ok": true,
      "item_count": 0,
      "duration_ms": 724,
      "error": null
    },
    {
      "site_id": "tophub",
      "site_name": "TopHub",
      "ok": true,
      "item_count": 3037,
      "duration_ms": 1036,
      "error": null
    },
    {
      "site_id": "zeli",
      "site_name": "Zeli",
      "ok": true,
      "item_count": 69,
      "duration_ms": 842,
      "error": null
    },
    {
      "site_id": "aihubtoday",
      "site_name": "AI HubToday",
      "ok": true,
      "item_count": 1,
      "duration_ms": 235,
      "error": null
    },
    {
      "site_id": "aibase",
      "site_name": "AIbase",
      "ok": true,
      "item_count": 20,
      "duration_ms": 5038,
      "error": null
    },
    {
      "site_id": "aihot",
      "site_name": "AI今日热榜",
      "ok": true,
      "item_count": 0,
      "duration_ms": 350,
      "error": null
    },
    {
      "site_id": "newsnow",
      "site_name": "NewsNow",
      "ok": true,
      "item_count": 142,
      "duration_ms": 1871,
      "error": null
    },
    {
      "site_id": "youtube",
      "site_name": "YouTube",
      "ok": true,
      "item_count": 45,
      "duration_ms": 288,
      "error": null
    },
    {
      "site_id": "xinzhiyuan",
      "site_name": "新智元",
      "ok": true,
      "item_count": 37,
      "duration_ms": 4507,
      "error": null
    },
    {
      "site_id": "wechat-rss",
      "site_name": "微信公众号",
      "ok": true,
      "item_count": 176,
      "duration_ms": 1602,
      "error": null
    }
  ],
  "successful_sites": 13,
  "failed_sites": [],
  "zero_item_sites": [
    "bestblogs",
    "aihot"
  ],
  "fetched_raw_items": 5071,
  "items_before_topic_filter": 45451,
  "items_in_24h": 840,
  "rss_opml": {
    "enabled": false,
    "path": null,
    "feed_total": 0,
    "effective_feed_total": 0,
    "ok_feeds": 0,
    "failed_feeds": [],
    "zero_item_feeds": [],
    "skipped_feeds": [],
    "replaced_feeds": [],
    "feeds": []
  }
}